congress/client.py
congress/fields.py
united_states_congress_python_api-0.0.2.dist-info/LICENSE
united_states_congress_python_api-0.0.2.dist-info/METADATA
united_states_congress_python_api-0.0.2.dist-info/WHEEL
united_states_congress_python_api-0.0.2.dist-info/top_level.txt
united_states_congress_python_api-0.0.2.dist-info/RECORD
