Metadata-Version: 2.1
Name: united-states-congress-python-api
Version: 0.0.2
Summary: UNKNOWN
Home-page: https://github.com/areed1192/united-states-congress-python-api
Author: Alex Reed
Author-email: coding.sigma@gmail.com
License: UNKNOWN
Platform: UNKNOWN
Classifier: Development Status :: 3 - Alpha
Classifier: Intended Audience :: Financial and Insurance Industry
Classifier: License :: OSI Approved :: MIT License
Classifier: Natural Language :: English
Classifier: Operating System :: OS Independent
Classifier: Programming Language :: Python :: 3
Classifier: Topic :: Office/Business :: News/Diary
Classifier: Intended Audience :: Science/Research
Classifier: Intended Audience :: Legal Industry
Requires-Python: >3.7
Requires-Dist: requests
